Metadata-Version: 1.0
Name: distributions-gr
Version: 0.1
Summary: Gaussian distributions
Home-page: UNKNOWN
Author: GunaSekhar Revuri
Author-email: gunarevuri@gmail.com
License: UNKNOWN
Platform: UNKNOWN
